LICENCE
MANIFEST.in
README.md
setup.cfg
setup.py
django_parse_push.egg-info/PKG-INFO
django_parse_push.egg-info/SOURCES.txt
django_parse_push.egg-info/dependency_links.txt
django_parse_push.egg-info/not-zip-safe
django_parse_push.egg-info/requires.txt
django_parse_push.egg-info/top_level.txt
parse_push/__init__.py
parse_push/client.py
parse_push/config.py
parse_push/enums.py
parse_push/fields.py
parse_push/managers.py
parse_push/models.py
parse_push/serializers.py
parse_push/urls.py
parse_push/views.py
parse_push/migrations/0001_initial.py
parse_push/migrations/0002_device_updated_at.py
parse_push/migrations/__init__.py
parse_push/tests/__init__.py
parse_push/tests/test_api.py