Metadata-Version: 1.0
Name: django-parse-push
Version: 0.2
Summary: Simple Django based wrapper for Parse Push API
Home-page: https://github.com/willandskill/django-parse-push
Author: Will & Skill AB
Author-email: info@willandskill.se
License: BSD licence, see LICENCE.txt
Keywords: django,parse,push,rest
Platform: UNKNOWN
